cnpm_webdriver_manager/__init__.py
cnpm_webdriver_manager/chrome.py
cnpm_webdriver_manager/firefox.py
cnpm_webdriver_manager/opera.py
cnpm_webdriver_manager/drivers/__init__.py
cnpm_webdriver_manager/drivers/chrome.py
cnpm_webdriver_manager/drivers/firefox.py
cnpm_webdriver_manager/drivers/opera.py
cnpm_webdriver_manager-4.0.2.dist-info/METADATA
cnpm_webdriver_manager-4.0.2.dist-info/WHEEL
cnpm_webdriver_manager-4.0.2.dist-info/licenses/LICENSE
cnpm_webdriver_manager-4.0.2.dist-info/RECORD
