Metadata-Version: 2.3
Name: cnpm-webdriver-manager
Version: 4.0.2
Summary: 基于 webdriver-manager，使用淘宝 npm 镜像下载浏览器驱动，仅适用于 Chrome、Firefox 和 Opera。
Project-URL: Homepage, https://github.com/GoldBadge/cnpm_webdriver_manager
Project-URL: Issues, https://github.com/GoldBadge/cnpm_webdriver_manager/issues
Author: GoldBadge
Maintainer: GoldBadge
License:                                  Apache License
Keywords: chromedriver,cnpm,geckodriver,npmmirror,operadriver,webdriver,浏览器驱动
Classifier: License :: OSI Approved :: Apache Software License
Classifier: Operating System :: MacOS
Classifier: Operating System :: Microsoft :: Windows
Classifier: Operating System :: POSIX
Classifier: Operating System :: Unix
Classifier: Programming Language :: Python :: 3.7
Classifier: Programming Language :: Python :: 3.8
Classifier: Programming Language :: Python :: 3.9
Classifier: Programming Language :: Python :: 3.10
Classifier: Programming Language :: Python :: 3.11
Classifier: Topic :: Software Development :: Libraries :: Python Modules
Requires-Python: >=3.7
Requires-Dist: webdriver-manager==4.0.2
